ai_capacity/__init__.py
ai_capacity/config.py
ai_capacity/agent/__init__.py
ai_capacity/agent/agent.py
ai_capacity/agent/deps.py
ai_capacity/agent/prompts.py
ai_capacity/cli/__init__.py
ai_capacity/cli/main.py
ai_capacity/tools/__init__.py
ai_capacity/tools/ec2.py
ai_capacity/tools/sagemaker.py
ai_capacity/ui/__init__.py
ai_capacity/ui/app.py
aws_ai_capacity-0.1.2.dist-info/METADATA
aws_ai_capacity-0.1.2.dist-info/WHEEL
aws_ai_capacity-0.1.2.dist-info/entry_points.txt
aws_ai_capacity-0.1.2.dist-info/licenses/LICENSE
aws_ai_capacity-0.1.2.dist-info/RECORD
