Metadata-Version: 2.4
Name: aws-ai-capacity
Version: 0.1.2
Summary: AWS GPU Capacity Management Agent with Pydantic AI
License-File: LICENSE
Requires-Python: >=3.12
Requires-Dist: aioboto3>=13.0
Requires-Dist: boto3>=1.35
Requires-Dist: chainlit>=1.3
Requires-Dist: pydantic-ai>=0.1.0
Requires-Dist: pydantic-settings>=2.6
Requires-Dist: pydantic>=2.10
Requires-Dist: python-dotenv>=1.0
Requires-Dist: rich>=13.9
Requires-Dist: structlog>=24.4
Requires-Dist: typer>=0.12
Provides-Extra: dev
Requires-Dist: moto[ec2,sagemaker]>=5.0; extra == 'dev'
Requires-Dist: pytest-asyncio>=0.24; extra == 'dev'
Requires-Dist: pytest>=8.3; extra == 'dev'
Requires-Dist: ruff>=0.8; extra == 'dev'
